{
	"instance" : {
		"generate" : "FGasquez 11/13/2017 22:27:04",
		"builder" : "FGasquez 11/13/2017 22:27:04",
		"name" : "FGasquez 11/13/2017 22:27:04",
		"builder:" : "FGasquez 11/13/2017 22:27:04",
		"exists" : "FGasquez 11/13/2017 22:27:04",
		"id" : "FGasquez 11/13/2017 22:27:04",
		"fileName:" : "FGasquez 11/13/2017 22:27:04",
		"builders" : "FGasquez 11/13/2017 22:27:04",
		"initialize" : "FGasquez 11/13/2017 22:27:04",
		"removeConflict" : "FGasquez 11/13/2017 22:27:04",
		"renderConfigOn:with:" : "FGasquez 11/13/2017 22:27:04",
		"fileName" : "FGasquez 11/13/2017 22:27:04",
		"renderWarningOn:" : "FGasquez 11/13/2017 22:27:04"
	},
	"class" : { }
}